2dcomboselector-0.2.0.dist-info/licenses/LICENSE
combo_selector/__init__.py
combo_selector/main.py
combo_selector/utils.py
combo_selector/core/orthogonality.py
combo_selector/core/orthogonality_utils.py
combo_selector/core/plot_utils.py
combo_selector/core/workers.py
combo_selector/resources/colormaps/Accent.png
combo_selector/resources/colormaps/Accent_r.png
combo_selector/resources/colormaps/Blues.png
combo_selector/resources/colormaps/Blues_r.png
combo_selector/resources/colormaps/BrBG.png
combo_selector/resources/colormaps/BrBG_r.png
combo_selector/resources/colormaps/BuGn.png
combo_selector/resources/colormaps/BuGn_r.png
combo_selector/resources/colormaps/BuPu.png
combo_selector/resources/colormaps/BuPu_r.png
combo_selector/resources/colormaps/CMRmap.png
combo_selector/resources/colormaps/CMRmap_r.png
combo_selector/resources/colormaps/Dark2.png
combo_selector/resources/colormaps/Dark2_r.png
combo_selector/resources/colormaps/GnBu.png
combo_selector/resources/colormaps/GnBu_r.png
combo_selector/resources/colormaps/Greens.png
combo_selector/resources/colormaps/Greens_r.png
combo_selector/resources/colormaps/Greys.png
combo_selector/resources/colormaps/Greys_r.png
combo_selector/resources/colormaps/OrRd.png
combo_selector/resources/colormaps/OrRd_r.png
combo_selector/resources/colormaps/Oranges.png
combo_selector/resources/colormaps/Oranges_r.png
combo_selector/resources/colormaps/PRGn.png
combo_selector/resources/colormaps/PRGn_r.png
combo_selector/resources/colormaps/Paired.png
combo_selector/resources/colormaps/Paired_r.png
combo_selector/resources/colormaps/Pastel1.png
combo_selector/resources/colormaps/Pastel1_r.png
combo_selector/resources/colormaps/Pastel2.png
combo_selector/resources/colormaps/Pastel2_r.png
combo_selector/resources/colormaps/PiYG.png
combo_selector/resources/colormaps/PiYG_r.png
combo_selector/resources/colormaps/PuBu.png
combo_selector/resources/colormaps/PuBuGn.png
combo_selector/resources/colormaps/PuBuGn_r.png
combo_selector/resources/colormaps/PuBu_r.png
2dcomboselector-0.2.0.dist-info/METADATA
2dcomboselector-0.2.0.dist-info/WHEEL
2dcomboselector-0.2.0.dist-info/entry_points.txt
2dcomboselector-0.2.0.dist-info/top_level.txt
2dcomboselector-0.2.0.dist-info/RECORD
